Metadata-Version: 2.1
Name: shellvaluepy
Version: 0.2.5
Summary: made by hminkoo10, discord : Crewmate#7777, email: hmin.koo10@gmail.com
Home-page: https://github.com/hminkoo10/shell_value
Author: hminkoo10
Author-email: hmin.koo10@gmail.com
License: MIT
Platform: UNKNOWN
